{
  "qProperty": {
    "qInfo": {
      "qId": "3e6f61ba-a983-4031-9d38-f6db0db2305c",
      "qType": "sheet"
    },
    "qMetaDef": {
      "title": "Labour Mobility - Indicator 5",
      "description": ""
    },
    "rank": 46,
    "thumbnail": {
      "qStaticContentUrlDef": {}
    },
    "columns": 24,
    "rows": 12,
    "cells": [
      {
        "name": "uKpUEw",
        "type": "barchart",
        "col": 0,
        "row": 0,
        "colspan": 23,
        "rowspan": 10,
        "bounds": {
          "y": 0,
          "x": 0,
          "width": 95.83333333333334,
          "height": 83.33333333333334
        }
      }
    ],
    "qChildListDef": {
      "qData": {
        "title": "/title"
      }
    },
    "customRowBase": 12,
    "gridResolution": "small",
    "layoutOptions": {
      "mobileLayout": "LIST"
    },
    "gridMode": "edit"
  },
  "qChildren": [
    {
      "qProperty": {
        "qInfo": {
          "qId": "uKpUEw",
          "qType": "barchart"
        },
        "qMetaDef": {},
        "qHyperCubeDef": {
          "qDimensions": [
            {
              "qDef": {
                "qGrouping": "N",
                "qFieldDefs": [
                  "=if (not isnull([Indicator 5Eures]), [ISO_code])"
                ],
                "qFieldLabels": [
                  ""
                ],
                "qSortCriterias": [
                  {
                    "qSortByNumeric": 1,
                    "qSortByAscii": 1,
                    "qSortByLoadOrder": 1,
                    "qSortByExpression": 1,
                    "qExpression": {
                      "qv": "Match([ISO_code],'AT','BE','BG','CY','CZ','DK','DE','EE','EL','ES','FI','FR','HR','HU','IE','IT','LT','LU','LV','MT','NL','PL','PT','RO','SE','SI','SK','CH','IS','LI','NO','UK')"
                    }
                  }
                ],
                "qNumberPresentations": [],
                "qActiveField": 0,
                "autoSort": false,
                "cId": "jGxwj",
                "othersLabel": "Otros"
              },
              "qNullSuppression": true,
              "qOtherTotalSpec": {
                "qOtherMode": "OTHER_OFF",
                "qOtherCounted": {
                  "qv": "10"
                },
                "qOtherLimit": {
                  "qv": "0"
                },
                "qOtherLimitMode": "OTHER_GE_LIMIT",
                "qForceBadValueKeeping": true,
                "qApplyEvenWhenPossiblyWrongResult": true,
                "qOtherSortMode": "OTHER_SORT_DESCENDING",
                "qTotalMode": "TOTAL_OFF",
                "qReferencedExpression": {}
              },
              "qOtherLabel": {
                "qv": "Otros"
              },
              "qTotalLabel": {},
              "qCalcCond": {},
              "qAttributeExpressions": [],
              "qAttributeDimensions": [],
              "qCalcCondition": {
                "qCond": {},
                "qMsg": {}
              }
            }
          ],
          "qMeasures": [
            {
              "qDef": {
                "qTags": [],
                "qGrouping": "N",
                "qDef": "if([Indicator 5Eures] = 'null', 0, [Indicator 5Eures]/100)",
                "qNumFormat": {
                  "qType": "F",
                  "qnDec": 2,
                  "qUseThou": 0,
                  "qFmt": "0.00%",
                  "qDec": ".",
                  "qThou": ","
                },
                "qAccumulate": 0,
                "qActiveExpression": 0,
                "qExpressions": [],
                "autoSort": true,
                "cId": "CPfHKaR",
                "numFormatFromTemplate": true,
                "isCustomFormatted": false
              },
              "qSortBy": {
                "qSortByNumeric": -1,
                "qSortByLoadOrder": 1,
                "qExpression": {}
              },
              "qAttributeExpressions": [
                {
                  "qExpression": "If(PA_EUR_JOB_PLA_IND5.2020 > 3.99, '#87aa7d', If(PA_EUR_JOB_PLA_IND5.2020 > 1.99 and PA_EUR_JOB_PLA_IND5.2020 <4.0, '#d0c131', '#b95545'))",
                  "qAttribute": true,
                  "id": "colorByExpression"
                }
              ],
              "qAttributeDimensions": [],
              "qCalcCond": {},
              "qCalcCondition": {
                "qCond": {},
                "qMsg": {}
              },
              "qTrendLines": [],
              "qMiniChartDef": {
                "qSortBy": {
                  "qExpression": {}
                },
                "qOtherTotalSpec": {
                  "qOtherMode": "OTHER_OFF",
                  "qOtherCounted": {},
                  "qOtherLimit": {},
                  "qOtherLimitMode": "OTHER_GT_LIMIT",
                  "qForceBadValueKeeping": true,
                  "qApplyEvenWhenPossiblyWrongResult": true,
                  "qOtherSortMode": "OTHER_SORT_DESCENDING",
                  "qTotalMode": "TOTAL_OFF",
                  "qReferencedExpression": {}
                },
                "qMaxNumberPoints": -1,
                "qAttributeExpressions": []
              }
            }
          ],
          "qInterColumnSortOrder": [
            1,
            0
          ],
          "qSuppressMissing": true,
          "qInitialDataFetch": [
            {
              "qLeft": 0,
              "qTop": 0,
              "qWidth": 17,
              "qHeight": 500
            }
          ],
          "qReductionMode": "N",
          "qMode": "S",
          "qPseudoDimPos": -1,
          "qNoOfLeftDims": -1,
          "qMaxStackedCells": 5000,
          "qCalcCond": {},
          "qTitle": {},
          "qCalcCondition": {
            "qCond": {},
            "qMsg": {}
          },
          "qColumnOrder": [],
          "qExpansionState": [],
          "qDynamicScript": [],
          "qLayoutExclude": {
            "qHyperCubeDef": {
              "qDimensions": [],
              "qMeasures": [],
              "qInterColumnSortOrder": [],
              "qInitialDataFetch": [],
              "qReductionMode": "N",
              "qMode": "S",
              "qPseudoDimPos": -1,
              "qNoOfLeftDims": -1,
              "qMaxStackedCells": 5000,
              "qCalcCond": {},
              "qTitle": {},
              "qCalcCondition": {
                "qCond": {},
                "qMsg": {}
              },
              "qColumnOrder": [],
              "qExpansionState": [],
              "qDynamicScript": []
            }
          }
        },
        "script": "",
        "refLine": {
          "refLines": [],
          "dimRefLines": []
        },
        "showTitles": true,
        "title": "Indicator [5]: Job placements vs. labour mobility",
        "subtitle": "",
        "footnote": "",
        "disableNavMenu": false,
        "showDetails": false,
        "showDetailsExpression": false,
        "showDisclaimer": true,
        "barGrouping": {
          "grouping": "grouped"
        },
        "orientation": "vertical",
        "scrollbar": "none",
        "scrollStartPos": 0,
        "gridLine": {
          "auto": true,
          "spacing": 2
        },
        "dataPoint": {
          "showLabels": true,
          "showSegmentLabels": false,
          "showTotalLabels": true
        },
        "color": {
          "auto": true,
          "mode": "byExpression",
          "formatting": {
            "numFormatFromTemplate": true
          },
          "useBaseColors": "off",
          "paletteColor": {
            "index": -1,
            "color": "#4073af"
          },
          "useDimColVal": true,
          "useMeasureGradient": true,
          "persistent": false,
          "expressionIsColor": true,
          "expressionLabel": "",
          "measureScheme": "sg",
          "reverseScheme": false,
          "dimensionScheme": "12",
          "autoMinMax": true,
          "measureMin": 0,
          "measureMax": 10,
          "colorExpression": "If([GT_EUR_JOB_PLA_IND5.2020] > 3.99, '#87aa7d', If([GT_EUR_JOB_PLA_IND5.2020] > 1.99 and [GT_EUR_JOB_PLA_IND5.2020] <4.0, '#d0c131', '#b95545'))"
        },
        "legend": {
          "show": true,
          "dock": "auto",
          "showTitle": true
        },
        "dimensionAxis": {
          "continuousAuto": true,
          "show": "labels",
          "label": "horizontal",
          "dock": "near",
          "axisDisplayMode": "max",
          "maxVisibleItems": 10
        },
        "preferContinuousAxis": true,
        "measureAxis": {
          "show": "labels",
          "dock": "near",
          "spacing": 0.5,
          "autoMinMax": false,
          "minMax": "max",
          "min": 0,
          "max": 0.15
        },
        "tooltip": {
          "auto": true,
          "hideBasic": false,
          "chart": {
            "style": {
              "size": "medium"
            }
          },
          "data": {}
        },
        "visualization": "barchart",
        "version": "1.13.2",
        "components": [],
        "showMiniChartForContinuousAxis": true
      },
      "qChildren": []
    }
  ]
}